flips/__init__.py
flips/flips.py
flips/rctn.py
flips/scheme.py
flips/util.py
flips-0.0.2.dist-info/METADATA
flips-0.0.2.dist-info/WHEEL
flips-0.0.2.dist-info/top_level.txt
flips-0.0.2.dist-info/RECORD
