Metadata-Version: 2.1
Name: flips
Version: 0.0.2
Summary: Flips solver
Home-page: https://gitlab.inria.fr/dlunz/flips
Author: Davin Lunz
Author-email: davin.lunz@inria.fr
License: cecill-2.1
Platform: UNKNOWN
Requires-Dist: tqdm
Requires-Dist: scipy
Requires-Dist: numpy
